chialisp_builder.py
quex_chialisp_builder-0.1.0.dist-info/LICENSE
quex_chialisp_builder-0.1.0.dist-info/METADATA
quex_chialisp_builder-0.1.0.dist-info/WHEEL
quex_chialisp_builder-0.1.0.dist-info/top_level.txt
quex_chialisp_builder-0.1.0.dist-info/RECORD
