Metadata-Version: 2.1
Name: quex-chialisp-builder
Version: 0.1.0
Summary: Allow on-demand builds of chialisp with recursive dependency checking.
Author-email: Richard Kiss <him@richardkiss.com>
License: Copyright 2023 by Richard Kiss
License-File: LICENSE
Requires-Dist: clvm-tools-rs
Requires-Dist: quex-runtime-builder ==0.0.1
